bykml/__init__.py
bykml/__main__.py
bykml/config.toml
bykml/kmlfactory.py
bykml-1.5.0.dist-info/LICENCE
bykml-1.5.0.dist-info/METADATA
bykml-1.5.0.dist-info/WHEEL
bykml-1.5.0.dist-info/entry_points.txt
bykml-1.5.0.dist-info/top_level.txt
bykml-1.5.0.dist-info/RECORD
